LICENSE
bgetcli/__init__.py
bgetcli/bget.py
bgetcli/downloader.py
bgetcli/runtime.py
bgetcli/utils.py
config-example.toml
bget-10.1.0.dist-info/LICENSE
bget-10.1.0.dist-info/WHEEL
bget-10.1.0.dist-info/entry_points.txt
bget-10.1.0.dist-info/METADATA
bget-10.1.0.dist-info/RECORD
