Metadata-Version: 2.1
Name: bget
Version: 10.1.0
Summary: bget - a python bilibili favourites batch downloader
Home-page: https://github.com/baobao1270/bget
License: MIT
Keywords: bilibili,terminal
Author: Joseph Chris
Author-email: joseph@josephcz.xyz
Requires-Python: >=3.8,<4.0
Classifier: License :: OSI Approved :: MIT License
Classifier: Operating System :: OS Independent
Classifier: Programming Language :: Python :: 3
Classifier: Programming Language :: Python :: 3.8
Classifier: Programming Language :: Python :: 3.9
Classifier: Programming Language :: Python :: 3.10
Classifier: Programming Language :: Python :: 3.11
Classifier: Programming Language :: Python :: 3
Requires-Dist: bgetlib (>=3.2.7)
Requires-Dist: toml (>=0.10.2)
Project-URL: Repository, https://github.com/baobao1270/bget.git
